{"net":"li","brandId":"886877","label":"eimec.es","followersNow":1243,"daily":[{"d":"2026-01-14","followers":null,"follows":22,"reach":null,"views":null,"inter":null,"posts":null,"stories":null,"storiesReach":null},{"d":"2026-01-15","followers":1060,"follows":2,"reach":73,"views":14,"inter":null,"posts":null,"stories":null,"storiesReach":null},{"d":"2026-01-16","followers":1058,"follows":-2,"reach":30,"views":null,"inter":null,"posts":null,"stories":null,"storiesReach":null},{"d":"2026-01-17","followers":1058,"follows":0,"reach":9,"views":null,"inter":null,"posts":null,"stories":null,"storiesReach":null},{"d":"2026-01-18","followers":1058,"follows":0,"reach":6,"views":3,"inter":null,"posts":null,"stories":null,"storiesReach":null},{"d":"2026-01-19","followers":1059,"follows":1,"reach":52,"views":9,"inter":null,"posts":null,"stories":null,"storiesReach":null},{"d":"2026-01-20","followers":1060,"follows":1,"reach":75,"views":9,"inter":null,"posts":null,"stories":null,"storiesReach":null},{"d":"2026-01-21","followers":1062,"follows":2,"reach":30,"views":3,"inter":null,"posts":null,"stories":null,"storiesReach":null},{"d":"2026-01-22","followers":1062,"follows":0,"reach":54,"views":10,"inter":73,"posts":1,"stories":null,"storiesReach":null},{"d":"2026-01-23","followers":1063,"follows":1,"reach":78,"views":1,"inter":null,"posts":null,"stories":null,"storiesReach":null},{"d":"2026-01-24","followers":1063,"follows":0,"reach":22,"views":null,"inter":null,"posts":null,"stories":null,"storiesReach":null},{"d":"2026-01-25","followers":1063,"follows":0,"reach":18,"views":null,"inter":null,"posts":null,"stories":null,"storiesReach":null},{"d":"2026-01-26","followers":1063,"follows":0,"reach":22,"views":1,"inter":null,"posts":null,"stories":null,"storiesReach":null},{"d":"2026-01-27","followers":1063,"follows":0,"reach":8,"views":1,"inter":null,"posts":null,"stories":null,"storiesReach":null},{"d":"2026-01-28","followers":1064,"follows":1,"reach":4,"views":2,"inter":null,"posts":null,"stories":null,"storiesReach":null},{"d":"2026-01-29","followers":1065,"follows":1,"reach":9,"views":null,"inter":null,"posts":null,"stories":null,"storiesReach":null},{"d":"2026-01-30","followers":1066,"follows":1,"reach":16,"views":6,"inter":null,"posts":null,"stories":null,"storiesReach":null},{"d":"2026-01-31","followers":1067,"follows":1,"reach":20,"views":6,"inter":null,"posts":null,"stories":null,"storiesReach":null},{"d":"2026-02-01","followers":1068,"follows":1,"reach":14,"views":null,"inter":null,"posts":null,"stories":null,"storiesReach":null},{"d":"2026-02-02","followers":1067,"follows":-1,"reach":106,"views":4,"inter":19,"posts":1,"stories":null,"storiesReach":null},{"d":"2026-02-03","followers":1070,"follows":3,"reach":62,"views":15,"inter":null,"posts":null,"stories":null,"storiesReach":null},{"d":"2026-02-04","followers":1072,"follows":2,"reach":138,"views":3,"inter":91,"posts":1,"stories":null,"storiesReach":null},{"d":"2026-02-05","followers":1075,"follows":3,"reach":95,"views":3,"inter":2,"posts":1,"stories":null,"storiesReach":null},{"d":"2026-02-06","followers":1075,"follows":0,"reach":81,"views":5,"inter":null,"posts":null,"stories":null,"storiesReach":null},{"d":"2026-02-07","followers":1074,"follows":-1,"reach":23,"views":null,"inter":null,"posts":null,"stories":null,"storiesReach":null},{"d":"2026-02-08","followers":1074,"follows":0,"reach":14,"views":null,"inter":null,"posts":null,"stories":null,"storiesReach":null},{"d":"2026-02-09","followers":1073,"follows":-1,"reach":76,"views":1,"inter":32,"posts":1,"stories":null,"storiesReach":null},{"d":"2026-02-10","followers":1074,"follows":1,"reach":161,"views":null,"inter":34,"posts":1,"stories":null,"storiesReach":null},{"d":"2026-02-11","followers":1076,"follows":2,"reach":97,"views":3,"inter":null,"posts":null,"stories":null,"storiesReach":null},{"d":"2026-02-12","followers":1077,"follows":1,"reach":49,"views":6,"inter":null,"posts":null,"stories":null,"storiesReach":null},{"d":"2026-02-13","followers":1078,"follows":1,"reach":110,"views":1,"inter":134,"posts":1,"stories":null,"storiesReach":null},{"d":"2026-02-14","followers":1079,"follows":1,"reach":79,"views":1,"inter":null,"posts":null,"stories":null,"storiesReach":null},{"d":"2026-02-15","followers":1080,"follows":1,"reach":27,"views":1,"inter":null,"posts":null,"stories":null,"storiesReach":null},{"d":"2026-02-16","followers":1082,"follows":2,"reach":224,"views":2,"inter":116,"posts":1,"stories":null,"storiesReach":null},{"d":"2026-02-17","followers":1081,"follows":-1,"reach":173,"views":21,"inter":null,"posts":null,"stories":null,"storiesReach":null},{"d":"2026-02-18","followers":1082,"follows":1,"reach":71,"views":1,"inter":null,"posts":null,"stories":null,"storiesReach":null},{"d":"2026-02-19","followers":1083,"follows":1,"reach":53,"views":4,"inter":null,"posts":null,"stories":null,"storiesReach":null},{"d":"2026-02-20","followers":1086,"follows":3,"reach":79,"views":13,"inter":null,"posts":null,"stories":null,"storiesReach":null},{"d":"2026-02-21","followers":1087,"follows":1,"reach":61,"views":null,"inter":null,"posts":null,"stories":null,"storiesReach":null},{"d":"2026-02-22","followers":1087,"follows":0,"reach":52,"views":null,"inter":null,"posts":null,"stories":null,"storiesReach":null},{"d":"2026-02-23","followers":1088,"follows":1,"reach":32,"views":2,"inter":null,"posts":null,"stories":null,"storiesReach":null},{"d":"2026-02-24","followers":1089,"follows":1,"reach":70,"views":1,"inter":20,"posts":1,"stories":null,"storiesReach":null},{"d":"2026-02-25","followers":1089,"follows":0,"reach":117,"views":13,"inter":15,"posts":1,"stories":null,"storiesReach":null},{"d":"2026-02-26","followers":1093,"follows":4,"reach":119,"views":9,"inter":25,"posts":1,"stories":null,"storiesReach":null},{"d":"2026-02-27","followers":1094,"follows":1,"reach":155,"views":2,"inter":25,"posts":1,"stories":null,"storiesReach":null},{"d":"2026-02-28","followers":1095,"follows":1,"reach":46,"views":1,"inter":null,"posts":null,"stories":null,"storiesReach":null},{"d":"2026-03-01","followers":1099,"follows":4,"reach":40,"views":null,"inter":null,"posts":null,"stories":null,"storiesReach":null},{"d":"2026-03-02","followers":1111,"follows":12,"reach":175,"views":7,"inter":84,"posts":1,"stories":null,"storiesReach":null},{"d":"2026-03-03","followers":1110,"follows":-1,"reach":121,"views":6,"inter":null,"posts":null,"stories":null,"storiesReach":null},{"d":"2026-03-04","followers":1112,"follows":2,"reach":53,"views":3,"inter":null,"posts":null,"stories":null,"storiesReach":null},{"d":"2026-03-05","followers":1113,"follows":1,"reach":59,"views":7,"inter":null,"posts":null,"stories":null,"storiesReach":null},{"d":"2026-03-06","followers":1126,"follows":13,"reach":194,"views":16,"inter":154,"posts":1,"stories":null,"storiesReach":null},{"d":"2026-03-07","followers":1124,"follows":-2,"reach":99,"views":11,"inter":null,"posts":null,"stories":null,"storiesReach":null},{"d":"2026-03-08","followers":1124,"follows":0,"reach":54,"views":1,"inter":null,"posts":null,"stories":null,"storiesReach":null},{"d":"2026-03-09","followers":1127,"follows":3,"reach":190,"views":2,"inter":11,"posts":1,"stories":null,"storiesReach":null},{"d":"2026-03-10","followers":1127,"follows":0,"reach":70,"views":1,"inter":16,"posts":1,"stories":null,"storiesReach":null},{"d":"2026-03-11","followers":1127,"follows":0,"reach":88,"views":9,"inter":null,"posts":null,"stories":null,"storiesReach":null},{"d":"2026-03-12","followers":1131,"follows":4,"reach":60,"views":5,"inter":null,"posts":null,"stories":null,"storiesReach":null},{"d":"2026-03-13","followers":1134,"follows":3,"reach":39,"views":2,"inter":null,"posts":null,"stories":null,"storiesReach":null},{"d":"2026-03-14","followers":1136,"follows":2,"reach":48,"views":3,"inter":null,"posts":null,"stories":null,"storiesReach":null},{"d":"2026-03-15","followers":1137,"follows":1,"reach":40,"views":1,"inter":null,"posts":null,"stories":null,"storiesReach":null},{"d":"2026-03-16","followers":1138,"follows":1,"reach":35,"views":null,"inter":null,"posts":null,"stories":null,"storiesReach":null},{"d":"2026-03-17","followers":1140,"follows":2,"reach":157,"views":1,"inter":37,"posts":1,"stories":null,"storiesReach":null},{"d":"2026-03-18","followers":1141,"follows":1,"reach":124,"views":2,"inter":null,"posts":null,"stories":null,"storiesReach":null},{"d":"2026-03-19","followers":1142,"follows":1,"reach":46,"views":1,"inter":null,"posts":null,"stories":null,"storiesReach":null},{"d":"2026-03-20","followers":1144,"follows":2,"reach":29,"views":14,"inter":null,"posts":null,"stories":null,"storiesReach":null},{"d":"2026-03-21","followers":1144,"follows":0,"reach":35,"views":null,"inter":null,"posts":null,"stories":null,"storiesReach":null},{"d":"2026-03-22","followers":1146,"follows":2,"reach":41,"views":null,"inter":null,"posts":null,"stories":null,"storiesReach":null},{"d":"2026-03-23","followers":1144,"follows":-2,"reach":115,"views":3,"inter":null,"posts":null,"stories":null,"storiesReach":null},{"d":"2026-03-24","followers":1146,"follows":2,"reach":32,"views":6,"inter":null,"posts":null,"stories":null,"storiesReach":null},{"d":"2026-03-25","followers":1146,"follows":0,"reach":77,"views":2,"inter":73,"posts":1,"stories":null,"storiesReach":null},{"d":"2026-03-26","followers":1146,"follows":0,"reach":46,"views":null,"inter":null,"posts":null,"stories":null,"storiesReach":null},{"d":"2026-03-27","followers":1147,"follows":1,"reach":34,"views":null,"inter":null,"posts":null,"stories":null,"storiesReach":null},{"d":"2026-03-28","followers":1148,"follows":1,"reach":26,"views":2,"inter":null,"posts":null,"stories":null,"storiesReach":null},{"d":"2026-03-29","followers":1148,"follows":0,"reach":26,"views":null,"inter":null,"posts":null,"stories":null,"storiesReach":null},{"d":"2026-03-30","followers":1151,"follows":3,"reach":84,"views":3,"inter":42,"posts":1,"stories":null,"storiesReach":null},{"d":"2026-03-31","followers":1149,"follows":-2,"reach":44,"views":null,"inter":null,"posts":null,"stories":null,"storiesReach":null},{"d":"2026-04-01","followers":1152,"follows":3,"reach":59,"views":1,"inter":null,"posts":null,"stories":null,"storiesReach":null},{"d":"2026-04-02","followers":1154,"follows":2,"reach":43,"views":1,"inter":null,"posts":null,"stories":null,"storiesReach":null},{"d":"2026-04-03","followers":1154,"follows":0,"reach":17,"views":null,"inter":null,"posts":null,"stories":null,"storiesReach":null},{"d":"2026-04-04","followers":1156,"follows":2,"reach":30,"views":1,"inter":null,"posts":null,"stories":null,"storiesReach":null},{"d":"2026-04-05","followers":1157,"follows":1,"reach":31,"views":1,"inter":null,"posts":null,"stories":null,"storiesReach":null},{"d":"2026-04-06","followers":1157,"follows":0,"reach":40,"views":null,"inter":null,"posts":null,"stories":null,"storiesReach":null},{"d":"2026-04-07","followers":1159,"follows":2,"reach":34,"views":5,"inter":null,"posts":null,"stories":null,"storiesReach":null},{"d":"2026-04-08","followers":1160,"follows":1,"reach":275,"views":9,"inter":92,"posts":1,"stories":null,"storiesReach":null},{"d":"2026-04-09","followers":1163,"follows":3,"reach":78,"views":4,"inter":null,"posts":null,"stories":null,"storiesReach":null},{"d":"2026-04-10","followers":1164,"follows":1,"reach":225,"views":4,"inter":148,"posts":1,"stories":null,"storiesReach":null},{"d":"2026-04-11","followers":1164,"follows":0,"reach":54,"views":null,"inter":null,"posts":null,"stories":null,"storiesReach":null},{"d":"2026-04-12","followers":1165,"follows":1,"reach":80,"views":null,"inter":null,"posts":null,"stories":null,"storiesReach":null},{"d":"2026-04-13","followers":1166,"follows":1,"reach":273,"views":7,"inter":28,"posts":1,"stories":null,"storiesReach":null},{"d":"2026-04-14","followers":1167,"follows":1,"reach":237,"views":5,"inter":32,"posts":1,"stories":null,"storiesReach":null},{"d":"2026-04-15","followers":1167,"follows":0,"reach":193,"views":2,"inter":null,"posts":null,"stories":null,"storiesReach":null},{"d":"2026-04-16","followers":1168,"follows":1,"reach":182,"views":null,"inter":152,"posts":2,"stories":null,"storiesReach":null},{"d":"2026-04-17","followers":1170,"follows":2,"reach":128,"views":2,"inter":null,"posts":null,"stories":null,"storiesReach":null},{"d":"2026-04-18","followers":1169,"follows":-1,"reach":86,"views":2,"inter":null,"posts":null,"stories":null,"storiesReach":null},{"d":"2026-04-19","followers":1169,"follows":0,"reach":71,"views":1,"inter":null,"posts":null,"stories":null,"storiesReach":null},{"d":"2026-04-20","followers":1171,"follows":2,"reach":85,"views":2,"inter":8,"posts":1,"stories":null,"storiesReach":null},{"d":"2026-04-21","followers":1174,"follows":3,"reach":117,"views":6,"inter":21,"posts":1,"stories":null,"storiesReach":null},{"d":"2026-04-22","followers":1174,"follows":0,"reach":141,"views":2,"inter":6,"posts":2,"stories":null,"storiesReach":null},{"d":"2026-04-23","followers":1179,"follows":5,"reach":403,"views":3,"inter":200,"posts":1,"stories":null,"storiesReach":null},{"d":"2026-04-24","followers":1177,"follows":-2,"reach":226,"views":2,"inter":49,"posts":1,"stories":null,"storiesReach":null},{"d":"2026-04-25","followers":1177,"follows":0,"reach":104,"views":null,"inter":null,"posts":null,"stories":null,"storiesReach":null},{"d":"2026-04-26","followers":1177,"follows":0,"reach":108,"views":null,"inter":null,"posts":null,"stories":null,"storiesReach":null},{"d":"2026-04-27","followers":1180,"follows":3,"reach":274,"views":12,"inter":26,"posts":1,"stories":null,"storiesReach":null},{"d":"2026-04-28","followers":1180,"follows":0,"reach":135,"views":9,"inter":null,"posts":null,"stories":null,"storiesReach":null},{"d":"2026-04-29","followers":1180,"follows":0,"reach":116,"views":3,"inter":6,"posts":1,"stories":null,"storiesReach":null},{"d":"2026-04-30","followers":1180,"follows":0,"reach":88,"views":2,"inter":null,"posts":null,"stories":null,"storiesReach":null},{"d":"2026-05-01","followers":1180,"follows":0,"reach":46,"views":3,"inter":null,"posts":null,"stories":null,"storiesReach":null},{"d":"2026-05-02","followers":1182,"follows":2,"reach":36,"views":1,"inter":null,"posts":null,"stories":null,"storiesReach":null},{"d":"2026-05-03","followers":1182,"follows":0,"reach":80,"views":null,"inter":9,"posts":1,"stories":null,"storiesReach":null},{"d":"2026-05-04","followers":1183,"follows":1,"reach":149,"views":7,"inter":null,"posts":null,"stories":null,"storiesReach":null},{"d":"2026-05-05","followers":1183,"follows":0,"reach":84,"views":null,"inter":null,"posts":null,"stories":null,"storiesReach":null},{"d":"2026-05-06","followers":1183,"follows":0,"reach":124,"views":12,"inter":1,"posts":1,"stories":null,"storiesReach":null},{"d":"2026-05-07","followers":1183,"follows":0,"reach":233,"views":1,"inter":171,"posts":1,"stories":null,"storiesReach":null},{"d":"2026-05-08","followers":1183,"follows":0,"reach":132,"views":6,"inter":null,"posts":null,"stories":null,"storiesReach":null},{"d":"2026-05-09","followers":1183,"follows":0,"reach":140,"views":null,"inter":null,"posts":null,"stories":null,"storiesReach":null},{"d":"2026-05-10","followers":1185,"follows":2,"reach":118,"views":2,"inter":null,"posts":null,"stories":null,"storiesReach":null},{"d":"2026-05-11","followers":1184,"follows":-1,"reach":135,"views":4,"inter":14,"posts":1,"stories":null,"storiesReach":null},{"d":"2026-05-12","followers":1184,"follows":0,"reach":108,"views":null,"inter":null,"posts":null,"stories":null,"storiesReach":null},{"d":"2026-05-13","followers":1185,"follows":1,"reach":91,"views":4,"inter":null,"posts":null,"stories":null,"storiesReach":null},{"d":"2026-05-14","followers":1188,"follows":3,"reach":48,"views":9,"inter":null,"posts":null,"stories":null,"storiesReach":null},{"d":"2026-05-15","followers":1193,"follows":5,"reach":68,"views":null,"inter":78,"posts":1,"stories":null,"storiesReach":null},{"d":"2026-05-16","followers":1195,"follows":2,"reach":70,"views":3,"inter":null,"posts":null,"stories":null,"storiesReach":null},{"d":"2026-05-17","followers":1196,"follows":1,"reach":41,"views":1,"inter":null,"posts":null,"stories":null,"storiesReach":null},{"d":"2026-05-18","followers":1213,"follows":17,"reach":216,"views":8,"inter":28,"posts":1,"stories":null,"storiesReach":null},{"d":"2026-05-19","followers":1213,"follows":0,"reach":170,"views":16,"inter":3,"posts":1,"stories":null,"storiesReach":null},{"d":"2026-05-20","followers":1213,"follows":0,"reach":97,"views":7,"inter":null,"posts":null,"stories":null,"storiesReach":null},{"d":"2026-05-21","followers":1215,"follows":2,"reach":86,"views":null,"inter":49,"posts":1,"stories":null,"storiesReach":null},{"d":"2026-05-22","followers":1215,"follows":0,"reach":142,"views":2,"inter":87,"posts":2,"stories":null,"storiesReach":null},{"d":"2026-05-23","followers":1216,"follows":1,"reach":117,"views":null,"inter":null,"posts":null,"stories":null,"storiesReach":null},{"d":"2026-05-24","followers":1216,"follows":0,"reach":118,"views":null,"inter":null,"posts":null,"stories":null,"storiesReach":null},{"d":"2026-05-25","followers":1216,"follows":0,"reach":150,"views":2,"inter":null,"posts":null,"stories":null,"storiesReach":null},{"d":"2026-05-26","followers":1216,"follows":0,"reach":197,"views":2,"inter":10,"posts":1,"stories":null,"storiesReach":null},{"d":"2026-05-27","followers":1217,"follows":1,"reach":161,"views":1,"inter":16,"posts":1,"stories":null,"storiesReach":null},{"d":"2026-05-28","followers":1218,"follows":1,"reach":112,"views":13,"inter":null,"posts":null,"stories":null,"storiesReach":null},{"d":"2026-05-29","followers":1220,"follows":2,"reach":86,"views":1,"inter":null,"posts":null,"stories":null,"storiesReach":null},{"d":"2026-05-30","followers":1220,"follows":0,"reach":53,"views":7,"inter":null,"posts":null,"stories":null,"storiesReach":null},{"d":"2026-05-31","followers":1221,"follows":1,"reach":47,"views":1,"inter":null,"posts":null,"stories":null,"storiesReach":null},{"d":"2026-06-01","followers":1235,"follows":14,"reach":113,"views":27,"inter":null,"posts":null,"stories":null,"storiesReach":null},{"d":"2026-06-02","followers":1236,"follows":1,"reach":74,"views":3,"inter":114,"posts":1,"stories":null,"storiesReach":null},{"d":"2026-06-03","followers":1236,"follows":0,"reach":126,"views":3,"inter":null,"posts":null,"stories":null,"storiesReach":null},{"d":"2026-06-04","followers":1236,"follows":0,"reach":102,"views":5,"inter":14,"posts":1,"stories":null,"storiesReach":null},{"d":"2026-06-05","followers":1235,"follows":-1,"reach":128,"views":7,"inter":null,"posts":null,"stories":null,"storiesReach":null},{"d":"2026-06-06","followers":1235,"follows":0,"reach":60,"views":1,"inter":null,"posts":null,"stories":null,"storiesReach":null},{"d":"2026-06-07","followers":1235,"follows":0,"reach":38,"views":null,"inter":null,"posts":null,"stories":null,"storiesReach":null},{"d":"2026-06-08","followers":1236,"follows":1,"reach":106,"views":1,"inter":null,"posts":1,"stories":null,"storiesReach":null},{"d":"2026-06-09","followers":1238,"follows":2,"reach":229,"views":6,"inter":21,"posts":2,"stories":null,"storiesReach":null},{"d":"2026-06-10","followers":1237,"follows":-1,"reach":72,"views":7,"inter":null,"posts":null,"stories":null,"storiesReach":null},{"d":"2026-06-11","followers":1239,"follows":2,"reach":62,"views":10,"inter":null,"posts":null,"stories":null,"storiesReach":null},{"d":"2026-06-12","followers":1238,"follows":-1,"reach":38,"views":2,"inter":null,"posts":null,"stories":null,"storiesReach":null},{"d":"2026-06-13","followers":1238,"follows":0,"reach":30,"views":null,"inter":null,"posts":null,"stories":null,"storiesReach":null},{"d":"2026-06-14","followers":1238,"follows":0,"reach":43,"views":null,"inter":null,"posts":null,"stories":null,"storiesReach":null},{"d":"2026-06-15","followers":1239,"follows":1,"reach":80,"views":2,"inter":32,"posts":1,"stories":null,"storiesReach":null},{"d":"2026-06-16","followers":1239,"follows":0,"reach":48,"views":2,"inter":null,"posts":null,"stories":null,"storiesReach":null},{"d":"2026-06-17","followers":1240,"follows":1,"reach":53,"views":null,"inter":null,"posts":null,"stories":null,"storiesReach":null},{"d":"2026-06-18","followers":1241,"follows":1,"reach":74,"views":1,"inter":59,"posts":1,"stories":null,"storiesReach":null},{"d":"2026-06-19","followers":1241,"follows":0,"reach":103,"views":2,"inter":null,"posts":null,"stories":null,"storiesReach":null},{"d":"2026-06-20","followers":1241,"follows":0,"reach":9,"views":null,"inter":null,"posts":null,"stories":null,"storiesReach":null},{"d":"2026-06-21","followers":1241,"follows":0,"reach":3,"views":null,"inter":null,"posts":null,"stories":null,"storiesReach":null},{"d":"2026-06-22","followers":1241,"follows":0,"reach":92,"views":4,"inter":25,"posts":1,"stories":null,"storiesReach":null},{"d":"2026-06-23","followers":1242,"follows":1,"reach":71,"views":5,"inter":null,"posts":null,"stories":null,"storiesReach":null},{"d":"2026-06-24","followers":1242,"follows":0,"reach":73,"views":1,"inter":null,"posts":null,"stories":null,"storiesReach":null},{"d":"2026-06-25","followers":1242,"follows":0,"reach":93,"views":2,"inter":24,"posts":1,"stories":null,"storiesReach":null},{"d":"2026-06-26","followers":1242,"follows":0,"reach":27,"views":1,"inter":null,"posts":null,"stories":null,"storiesReach":null},{"d":"2026-06-27","followers":1242,"follows":0,"reach":17,"views":null,"inter":null,"posts":null,"stories":null,"storiesReach":null},{"d":"2026-06-28","followers":1242,"follows":0,"reach":25,"views":null,"inter":null,"posts":null,"stories":null,"storiesReach":null},{"d":"2026-06-29","followers":1242,"follows":0,"reach":33,"views":4,"inter":null,"posts":null,"stories":null,"storiesReach":null},{"d":"2026-06-30","followers":1243,"follows":1,"reach":21,"views":null,"inter":32,"posts":1,"stories":null,"storiesReach":null},{"d":"2026-07-01","followers":1243,"follows":0,"reach":34,"views":null,"inter":null,"posts":null,"stories":null,"storiesReach":null},{"d":"2026-07-02","followers":1243,"follows":0,"reach":64,"views":10,"inter":31,"posts":1,"stories":null,"storiesReach":null},{"d":"2026-07-03","followers":1243,"follows":0,"reach":88,"views":null,"inter":3,"posts":1,"stories":null,"storiesReach":null},{"d":"2026-07-04","followers":1244,"follows":1,"reach":16,"views":1,"inter":null,"posts":null,"stories":null,"storiesReach":null},{"d":"2026-07-05","followers":1244,"follows":0,"reach":28,"views":1,"inter":null,"posts":null,"stories":null,"storiesReach":null},{"d":"2026-07-06","followers":1244,"follows":0,"reach":15,"views":1,"inter":3,"posts":1,"stories":null,"storiesReach":null},{"d":"2026-07-07","followers":1243,"follows":-1,"reach":11,"views":7,"inter":null,"posts":null,"stories":null,"storiesReach":null}],"posts":[{"id":"urn:li:ugcPost:7420179165972209664","date":"2026-01-22T19:02","fmt":"Carrusel","title":"Ya es oficial! ✨ La doctora Silvia Costa se incorpora al equipo docente de EIMEC 🎉 Con 5 años de experiencia e","image":"https://media.licdn.com/dms/image/v2/D4E10AQEiVOu3Kv7E7w/image-shrink_1280/B4EZvnFfR5IkAc-/0/1769108534989?e=1778130000&v=beta&t=ouQQ0TQZCoMMJKpEBE2e30QakFm5btODlXoOrNuMWN4","url":"https://www.linkedin.com/feed/update/urn:li:ugcPost:7420179165972209664","reach":354,"views":null,"inter":null,"likes":17,"comments":1,"saves":null,"shares":2},{"id":"urn:li:ugcPost:7424087400026525696","date":"2026-02-02T13:52","fmt":"Post","title":"📅 El próximo 26 de febrero, en EIMEC Barcelona, reuniremos a profesionales del sector en una sesión diseñada p","image":null,"url":"https://www.linkedin.com/feed/update/urn:li:ugcPost:7424087400026525696","reach":279,"views":null,"inter":null,"likes":4,"comments":null,"saves":null,"shares":4},{"id":"urn:li:ugcPost:7424493077253423104","date":"2026-02-04T09:00","fmt":"Carrusel","title":"En EIMEC seguimos apostando por ser un punto de encuentro para la formación médica y la innovación en medicina","image":"https://media.licdn.com/dms/image/v2/D4E22AQEcMLvZ9f0pZQ/feedshare-shrink_2048_1536/B4EZwkZGwzJgAk-/0/1770137088345?e=1779321600&v=beta&t=eD8RlANmq2V2QP1Nper1zByQ9nCpca1ou4c4gEzWJxU","url":"https://www.linkedin.com/feed/update/urn:li:ugcPost:7424493077253423104","reach":597,"views":null,"inter":null,"likes":17,"comments":null,"saves":null,"shares":4},{"id":"urn:li:ugcPost:7425251185713983488","date":"2026-02-05T18:57","fmt":"Carrusel","title":"La regeneración facial da un paso más cuando la biotecnología y la práctica clínica real se integran en un mis","image":"https://media.licdn.com/dms/image/v2/D4E10AQHJdL1dWIW2Mg/image-shrink_1280/B4EZwvKSvKJAAc-/0/1770317753757?e=1770962400&v=beta&t=adDULMHNhTvv-D5njEgO0zEpblKvL6FPTa8u3K7wGyI","url":"https://www.linkedin.com/feed/update/urn:li:ugcPost:7425251185713983488","reach":25,"views":null,"inter":null,"likes":1,"comments":null,"saves":null,"shares":null},{"id":"urn:li:ugcPost:7426669176859029504","date":"2026-02-09T16:51","fmt":"Carrusel","title":"Hoy hemos tenido el placer de recibir a la Dra. @Daniela Fajardo, de la mano de @ISDIN, quien ha impartido una","image":"https://media.licdn.com/dms/image/v2/D4E22AQGZ05XvK44z8g/feedshare-shrink_2048_1536/B4EZxDUQivKAAk-/0/1770655911683?e=1779321600&v=beta&t=QXZ6EW3P7mLiq6EIK1JJWBJeI7hFX_2xkWpqcsJChsU","url":"https://www.linkedin.com/feed/update/urn:li:ugcPost:7426669176859029504","reach":209,"views":null,"inter":null,"likes":8,"comments":1,"saves":null,"shares":1},{"id":"urn:li:ugcPost:7426967196561539072","date":"2026-02-10T12:36","fmt":"Carrusel","title":"Hoy hemos recibido en EIMEC a un grupo internacional de estudiantes del ámbito de la sanidad procedentes de Ir","image":"https://media.licdn.com/dms/image/v2/D4E22AQEYrZKmyYtocA/feedshare-shrink_2048_1536/B4EZxHjTdLK8Ak-/0/1770726965627?e=1779321600&v=beta&t=5IOQk_tQO9zSsSfEuSRgJwQTHXRg4xi7s8PZuroA7-s","url":"https://www.linkedin.com/feed/update/urn:li:ugcPost:7426967196561539072","reach":300,"views":null,"inter":null,"likes":11,"comments":null,"saves":null,"shares":3},{"id":"urn:li:ugcPost:7428011898073350144","date":"2026-02-13T09:47","fmt":"Carrusel","title":"🌍 EIMEC amplía fronteras. Kuwait, nuevo destino internacional. La formación médica estética de EIMEC continúa ","image":"https://media.licdn.com/dms/image/v2/D4E22AQEXUQNerHYfgg/feedshare-shrink_2048_1536/B4EZxWZb1IIgAo-/0/1770976035284?e=1779321600&v=beta&t=Lq5FsvBHOBazLWxY0U1-kA3y72VWKZoM2NuC03tHv_M","url":"https://www.linkedin.com/feed/update/urn:li:ugcPost:7428011898073350144","reach":264,"views":null,"inter":null,"likes":12,"comments":null,"saves":null,"shares":3},{"id":"urn:li:ugcPost:7429161323072151552","date":"2026-02-16T13:54","fmt":"Carrusel","title":"En el Congreso de la @Sociedad Española de Medicina Estética 2026 hemos tenido la oportunidad de volver a cone","image":"https://media.licdn.com/dms/image/v2/D4E22AQGsUAUVopHHYg/feedshare-shrink_2048_1536/B4EZxmu1DeIkAk-/0/1771250078863?e=1779321600&v=beta&t=mBUTTBfB8_VmhedPvdy7f9xSzOgV_CEAz0YYFf0RI6c","url":"https://www.linkedin.com/feed/update/urn:li:ugcPost:7429161323072151552","reach":364,"views":null,"inter":null,"likes":10,"comments":null,"saves":null,"shares":2},{"id":"urn:li:ugcPost:7432139015773913088","date":"2026-02-24T19:07","fmt":"Vídeo","title":"Durante el congreso tuvimos la oportunidad de reencontrarnos con muchos de nuestros exalumnos y conversar sobr","image":"https://media.licdn.com/dms/image/v2/D4E10AQGgZ6Ybw7hL7w/videocover-high/B4EZyRC.k6GsBE-/0/1771960010962?e=1780797600&v=beta&t=3NTkTWdkyCFh5FgYMd87aFovZd8VFIn6Gk0nd2sOwUQ","url":"https://www.linkedin.com/feed/update/urn:li:ugcPost:7432139015773913088","reach":216,"views":null,"inter":null,"likes":9,"comments":null,"saves":null,"shares":2},{"id":"urn:li:ugcPost:7432417262428504064","date":"2026-02-25T13:32","fmt":"Carrusel","title":"Esta semana recibimos a @Croma-Pharma en EIMEC para una jornada de alto nivel científico dentro del programa d","image":"https://media.licdn.com/dms/image/v2/D4E22AQG_R3r0JRFl4g/feedshare-image-high-res/B4EZyVAG.8IEAU-/0/1772026360654?e=1781740800&v=beta&t=cuQqOe9rJCst_B4dQU9BkZjwmnQqdegoz9gpHqJ_aVM","url":"https://www.linkedin.com/feed/update/urn:li:ugcPost:7432417262428504064","reach":107,"views":null,"inter":null,"likes":6,"comments":null,"saves":null,"shares":1},{"id":"urn:li:ugcPost:7432861141200015360","date":"2026-02-26T18:56","fmt":"Carrusel","title":"💉 Convocatoria abierta | Máster 2026–2027 en Medicina Estética Facial En EIMEC abrimos oficialmente la inscrip","image":"https://media.licdn.com/dms/image/v2/D4E10AQGP_xPtW8hvzw/image-shrink_1280/B4EZybTmkhGsAc-/0/1772132133475?e=1780797600&v=beta&t=s2yYsRSaCGf6atF3dKkMMK3lGw2k8GHHb1zNoXTm8EQ","url":"https://www.linkedin.com/feed/update/urn:li:ugcPost:7432861141200015360","reach":163,"views":null,"inter":null,"likes":11,"comments":null,"saves":null,"shares":3},{"id":"urn:li:ugcPost:7433164312149618688","date":"2026-02-27T15:01","fmt":"Carrusel","title":"Esta semana en EIMEC tuvimos el privilegio de recibir a @Galderma en nuestra sala de conferencias para una jor","image":"https://media.licdn.com/dms/image/v2/D4E22AQHwu6vq127KnA/feedshare-image-high-res/B4EZyfnheWJsAU-/0/1772204465705?e=1781740800&v=beta&t=oMCzHJgBEUeEErVLuX3DPksEQisEumT78_eXXS_AxYo","url":"https://www.linkedin.com/feed/update/urn:li:ugcPost:7433164312149618688","reach":149,"views":null,"inter":null,"likes":9,"comments":null,"saves":null,"shares":null},{"id":"urn:li:ugcPost:7434248124921008129","date":"2026-03-02T14:47","fmt":"Carrusel","title":"El pasado 26 de febrero celebramos en EIMEC la jornada presencial “Regeneración Facial 360º: Cuando los exosom","image":"https://media.licdn.com/dms/image/v2/D4E22AQEuudcESaw98g/feedshare-image-high-res/B4EZyvBRd0GgAU-/0/1772462873196?e=1781740800&v=beta&t=gHRIpV7oPdV0buWrN_0M7lfiBPhK-1CURL4wGG8XhH8","url":"https://www.linkedin.com/feed/update/urn:li:ugcPost:7434248124921008129","reach":417,"views":null,"inter":null,"likes":22,"comments":2,"saves":null,"shares":3},{"id":"urn:li:ugcPost:7435667609867489280","date":"2026-03-06T12:48","fmt":"Carrusel","title":"📅 Hoy en EIMEC hemos tenido el placer de acoger una jornada formativa junto a @Teoxane España, centrada en la ","image":"https://media.licdn.com/dms/image/v2/D4E22AQF_Mu0tb60GVw/feedshare-image-high-res/B4EZzDMSUAJAAU-/0/1772801304537?e=1781740800&v=beta&t=uPLfrmdNwve5ji9ko8ZUE83HupwM2rGZNKkZ2T6dsmg","url":"https://www.linkedin.com/feed/update/urn:li:ugcPost:7435667609867489280","reach":546,"views":null,"inter":null,"likes":23,"comments":1,"saves":null,"shares":3},{"id":"urn:li:share:7436808885388247040","date":"2026-03-09T17:00","fmt":"Imagen","title":"Hoy, 9 de marzo, hemos celebrado en EIMEC una masterclass teórica en colaboración con @Paula Alonso Bahamonde,","image":"https://media.licdn.com/dms/image/v2/D4E22AQEXzL6XZPZuhg/feedshare-image-high-res/B4EZzTaRaGJMAU-/0/1773073406289?e=1781740800&v=beta&t=L2iqhO_rArr-91D8r8k5VAmyj6mDZnTp3AKK7lV3CkU","url":"https://www.linkedin.com/feed/update/urn:li:share:7436808885388247040","reach":175,"views":null,"inter":null,"likes":6,"comments":null,"saves":null,"shares":1},{"id":"urn:li:ugcPost:7437212301306449920","date":"2026-03-10T19:06","fmt":"Vídeo","title":"El Dr. Randall apostó por el Posgrado en Medicina Estética Facial en un momento clave de su carrera. Lo que em","image":"https://media.licdn.com/dms/image/v2/D4E10AQG4_6-S1vFEzw/ads-video-thumbnail_720_1280/B4EZzZJBuwJUAg-/0/1773169548519?e=1780797600&v=beta&t=Ea4afTFF2NSenPuhGCOi4gSLYNodERjhOGe74R1Pa-I","url":"https://www.linkedin.com/feed/update/urn:li:ugcPost:7437212301306449920","reach":221,"views":null,"inter":null,"likes":8,"comments":null,"saves":null,"shares":2},{"id":"urn:li:ugcPost:7439666060229775361","date":"2026-03-17T13:36","fmt":"Carrusel","title":"Ayer, 16 de marzo, vivimos una nueva jornada formativa en EIMEC centrada en la innovación en medicina estética","image":"https://media.licdn.com/dms/image/v2/D4E22AQHCDJID-kcvtg/feedshare-image-high-res/B4EZz8A2oFJcAU-/0/1773754608823?e=1781740800&v=beta&t=7f69FdfctGBGGOTvE68w1qMJsumMOEbjKavWFW9BpDU","url":"https://www.linkedin.com/feed/update/urn:li:ugcPost:7439666060229775361","reach":250,"views":null,"inter":null,"likes":13,"comments":null,"saves":null,"shares":1},{"id":"urn:li:ugcPost:7442538480515039233","date":"2026-03-25T19:00","fmt":"Carrusel","title":"Hay formaciones que se quedan en el recuerdo no solo por lo que aprendes, sino por lo que vives ✨ CAAME es una","image":"https://media.licdn.com/dms/image/v2/D4E22AQFmfb8CWgv2FA/feedshare-shrink_1280/B4EZ0k1MJAHAAM-/0/1774439417501?e=1784160000&v=beta&t=FmKNiv3dMiWiik1XvzS_zCEOzS8rHjvb5GTYLh3jWzE","url":"https://www.linkedin.com/feed/update/urn:li:ugcPost:7442538480515039233","reach":279,"views":null,"inter":null,"likes":13,"comments":null,"saves":null,"shares":3},{"id":"urn:li:ugcPost:7444409107333259264","date":"2026-03-30T15:44","fmt":"Carrusel","title":"Hoy en EIMEC hemos tenido el placer de contar con @Skymedic en un workshop especializado en técnicas láser apl","image":"https://media.licdn.com/dms/image/v2/D4D22AQG_l1rIzFW4Ig/feedshare-shrink_1280/B4DZ0_aokiKQAQ-/0/1774885440319?e=1784160000&v=beta&t=qyzNnF-BXgbXl5BG8HV_OysV6jZr6_bmIW-LVoBbC04","url":"https://www.linkedin.com/feed/update/urn:li:ugcPost:7444409107333259264","reach":236,"views":null,"inter":null,"likes":8,"comments":null,"saves":null,"shares":2},{"id":"urn:li:ugcPost:7447553417071284224","date":"2026-04-08T07:58","fmt":"Carrusel","title":"Como cada año, paramos para alinear 🔄 Dedicamos el día de ayer a revisar objetivos, coordinar equipos y asegur","image":"https://media.licdn.com/dms/image/v2/D4E22AQHzU10n4mK58A/feedshare-shrink_1280/B4EZ1sGWowH0AM-/0/1775635100204?e=1784160000&v=beta&t=hNo4PH_qGphhA0edMnauDrr50aAKQd-VbKMhGk9qgto","url":"https://www.linkedin.com/feed/update/urn:li:ugcPost:7447553417071284224","reach":374,"views":null,"inter":null,"likes":16,"comments":null,"saves":null,"shares":6},{"id":"urn:li:ugcPost:7448291620610879489","date":"2026-04-10T08:51","fmt":"Carrusel","title":"Celebrar también forma parte de construir equipo 🎉 Hemos tenido la suerte de compartir estos días algo más que","image":"https://media.licdn.com/dms/image/v2/D4E22AQEexNCiUXQ6vA/feedshare-shrink_1280/B4EZ12lwYsHYAM-/0/1775811103335?e=1784160000&v=beta&t=wUaxoVg9yIipWOHV0vGpYRLOLKg1g2Owr1cm4DgrkQo","url":"https://www.linkedin.com/feed/update/urn:li:ugcPost:7448291620610879489","reach":372,"views":null,"inter":null,"likes":14,"comments":1,"saves":null,"shares":3},{"id":"urn:li:share:7449378547552538624","date":"2026-04-13T08:50","fmt":"Imagen","title":"¡Seguimos creciendo como equipo! @Camila Cerfoglio se incorpora a EIMEC para reforzar el área de administració","image":"https://media.licdn.com/dms/image/v2/D4E22AQFE1Jw1cEJkbw/feedshare-shrink_1280/B4EZ2GCT56HsAQ-/0/1776070247185?e=1784160000&v=beta&t=lX6G5-9ol3NRoFeHenIjq2UN977-BciiGmFN-hVSXbw","url":"https://www.linkedin.com/feed/update/urn:li:share:7449378547552538624","reach":361,"views":null,"inter":null,"likes":13,"comments":1,"saves":null,"shares":2},{"id":"urn:li:ugcPost:7449880714700873728","date":"2026-04-14T18:06","fmt":"Vídeo","title":"💬 Si tu también quieres vivir la experiencia, comenta “CAAME” y nos pondremos en contacto personalmente. -----","image":"https://media.licdn.com/dms/image/v2/D4E10AQFp-ghmDP7J-Q/ads-video-thumbnail_720_1280/B4EZ2NK9VfJwAo-/0/1776189958854?e=1783400400&v=beta&t=nRgcur8NPfddV5S-U-Xkqumq2_8LzNg7CeTLMRdL2qg","url":"https://www.linkedin.com/feed/update/urn:li:ugcPost:7449880714700873728","reach":262,"views":null,"inter":null,"likes":8,"comments":1,"saves":null,"shares":4},{"id":"urn:li:ugcPost:7450531703330123777","date":"2026-04-16T13:13","fmt":"Post","title":"✨ Nueva formación en EIMEC en colaboración con Real Lasting El próximo 27 de abril a las 16:00 h, desde EIMEC ","image":null,"url":"https://www.linkedin.com/feed/update/urn:li:ugcPost:7450531703330123777","reach":46,"views":null,"inter":null,"likes":null,"comments":null,"saves":null,"shares":null},{"id":"urn:li:ugcPost:7450604514656546816","date":"2026-04-16T18:02","fmt":"Documento","title":"Un médico sin criterio clínico no falla en la técnica. Falla en la decisión. En medicina estética, el riesgo n","image":null,"url":"https://www.linkedin.com/feed/update/urn:li:ugcPost:7450604514656546816","reach":243,"views":null,"inter":null,"likes":8,"comments":null,"saves":null,"shares":4},{"id":"urn:li:ugcPost:7452015622881689600","date":"2026-04-20T15:29","fmt":"Post","title":"✨ Nueva formación en EIMEC en colaboración con Real Lasting El próximo 27 de abril a las 16:00 h, desde EIMEC ","image":null,"url":"https://www.linkedin.com/feed/update/urn:li:ugcPost:7452015622881689600","reach":116,"views":null,"inter":null,"likes":2,"comments":null,"saves":null,"shares":null},{"id":"urn:li:ugcPost:7452376594360332288","date":"2026-04-21T15:23","fmt":"Documento","title":"Estas son algunas de las opiniones de médicos que se han formado con nosotros 👩🏻‍⚕️👨🏽‍⚕️ En EIMEC, la mejora c","image":null,"url":"https://www.linkedin.com/feed/update/urn:li:ugcPost:7452376594360332288","reach":87,"views":null,"inter":null,"likes":1,"comments":null,"saves":null,"shares":null},{"id":"urn:li:share:7452590861420408832","date":"2026-04-22T05:35","fmt":"Texto","title":"Una conversación muy interesante y muy educativa.","image":null,"url":"https://www.linkedin.com/feed/update/urn:li:share:7452590861420408832","reach":81,"views":null,"inter":null,"likes":3,"comments":null,"saves":null,"shares":null},{"id":"urn:li:ugcPost:7452719986239758337","date":"2026-04-22T14:08","fmt":"Post","title":"Únete a este webinar online para que te expliquen en detalle el funcionamiento del Posgrado en ARGENTINA 🇦🇷 y ","image":null,"url":"https://www.linkedin.com/feed/update/urn:li:ugcPost:7452719986239758337","reach":112,"views":null,"inter":null,"likes":2,"comments":null,"saves":null,"shares":null},{"id":"urn:li:ugcPost:7453025774959489024","date":"2026-04-23T10:23","fmt":"Carrusel","title":"🎉 Ayer celebramos 4 años de EIMEC en nuestra sede de La Barceloneta. Cuando inauguramos este espacio, no fue s","image":"https://media.licdn.com/dms/image/v2/D4E22AQEcZ95oa9glFA/feedshare-image-high-res/B4EZ253bZ_J8AU-/0/1776939808660?e=1785369600&v=beta&t=vmQv1Pkj_GqourIZxRYZ3zw2EgIxxfhqxQMGi8XyVu0","url":"https://www.linkedin.com/feed/update/urn:li:ugcPost:7453025774959489024","reach":433,"views":null,"inter":null,"likes":18,"comments":null,"saves":null,"shares":3},{"id":"urn:li:share:7453329630389985280","date":"2026-04-24T06:31","fmt":"Imagen","title":"Hoy queremos reconocer a quienes dan sentido a lo que hacemos cada día: nuestro equipo docente 🥼 Gracias por c","image":"https://media.licdn.com/dms/image/v2/D4E22AQFH7hzhwBaYAQ/feedshare-image-high-res/B4EZ2.LzQ.J0AU-/0/1777012258975?e=1785369600&v=beta&t=h5UJGLbhYgllMkMm0QboFrsjMIG4IujglDW-BGRQhy0","url":"https://www.linkedin.com/feed/update/urn:li:share:7453329630389985280","reach":419,"views":null,"inter":null,"likes":20,"comments":1,"saves":null,"shares":4},{"id":"urn:li:ugcPost:7454555718415998977","date":"2026-04-27T15:43","fmt":"Carrusel","title":"Hoy en EIMEC vivimos una jornada muy enriquecedora junto a Real Lasting dedicada a medicina regenerativa aplic","image":"https://media.licdn.com/dms/image/v2/D4E22AQFZ5rqUIh3G5g/feedshare-image-high-res/B4EZ3Pm6xTIAAc-/0/1777304579915?e=1785369600&v=beta&t=OqATaaesyF7ofCM5yZTuCevEgjvxk9uhIhN2Al2sLHY","url":"https://www.linkedin.com/feed/update/urn:li:ugcPost:7454555718415998977","reach":128,"views":null,"inter":null,"likes":3,"comments":null,"saves":null,"shares":null},{"id":"urn:li:share:7455187524697862145","date":"2026-04-29T09:33","fmt":"Artículo","title":"Nos estrenamos en prensa ✨ Muy felices de compartir nuestra primera aparición en Para Ti, una de las revistas ","image":"https://media.licdn.com/dms/image/v2/D4E22AQHfqZ6f7BAOlg/feedshare-shrink_1280/B4EZ3Yli8AJcAM-/0/1777455215537?e=1785369600&v=beta&t=NADvAyE5W2PeT5yQJtU8ftjH0lUqy3ZupaBV_sD5odI","url":"https://www.linkedin.com/feed/update/urn:li:share:7455187524697862145","reach":108,"views":null,"inter":null,"likes":null,"comments":null,"saves":null,"shares":null},{"id":"urn:li:ugcPost:7456765765724094464","date":"2026-05-03T18:04","fmt":"Vídeo","title":"5 días intensivos para aprender haciendo con el Curso de Medicina Estética Facial. Un curso 90% práctico para ","image":"https://media.licdn.com/dms/image/v2/D4E10AQHYULPLrapp7Q/ads-video-thumbnail_720_1280/B4EZ3vA4G3HUAU-/0/1777831481716?e=1784084400&v=beta&t=U6nww4FEC_Ub31SM1LmF8EwsIQwnR0gLE04oH6OAnPA","url":"https://www.linkedin.com/feed/update/urn:li:ugcPost:7456765765724094464","reach":130,"views":null,"inter":null,"likes":4,"comments":null,"saves":null,"shares":null},{"id":"urn:li:share:7457722184028045312","date":"2026-05-06T09:25","fmt":"Artículo","title":"📅 El 14 de mayo organizamos un webinar de 30 minutos para presentar el Máster Avanzado en Innovación y Práctic","image":null,"url":"https://www.linkedin.com/feed/update/urn:li:share:7457722184028045312","reach":542,"views":null,"inter":null,"likes":null,"comments":null,"saves":null,"shares":null},{"id":"urn:li:ugcPost:7458088541621911553","date":"2026-05-07T09:41","fmt":"Carrusel","title":"✨ Seguimos creando conexiones internacionales en medicina estética. Hemos firmado un convenio de colaboración ","image":"https://media.licdn.com/dms/image/v2/D4E22AQGW_-ZnBfkgMw/feedshare-image-high-res/B4EZ4Bz_j8IAAY-/0/1778146868060?e=1785369600&v=beta&t=YpTc_LnKFMwO5Dwucnq2AHEn2h2YJGaMOXAAPjq24Ks","url":"https://www.linkedin.com/feed/update/urn:li:ugcPost:7458088541621911553","reach":400,"views":null,"inter":null,"likes":17,"comments":null,"saves":null,"shares":3},{"id":"urn:li:ugcPost:7459610904461004802","date":"2026-05-11T14:30","fmt":"Carrusel","title":"✨ El pasado 9 de mayo, tuvimos el placer de recibir en EIMEC a @Merz Aesthetics para una jornada científica ce","image":"https://media.licdn.com/dms/image/v2/D4E22AQH50-bmxd3gOg/feedshare-image-high-res/B4EZ4Xcli4H0AY-/0/1778509830701?e=1785369600&v=beta&t=ch0uBHRxV2qnN2wXBqzyCV3cnlG5gGao32HOQ1ytbFA","url":"https://www.linkedin.com/feed/update/urn:li:ugcPost:7459610904461004802","reach":92,"views":null,"inter":null,"likes":3,"comments":null,"saves":null,"shares":null},{"id":"urn:li:ugcPost:7461069359113867264","date":"2026-05-15T15:05","fmt":"Carrusel","title":"EIMEC llega al Congreso SIME con una beca para médicos de todo el mundo 🌍 El 47° Congreso SIME se celebra del ","image":"https://media.licdn.com/dms/image/v2/D4E22AQEwWPY3uRGiLw/feedshare-shrink_1280/B4EZ4sLBz9JgAM-/0/1778857549582?e=1785369600&v=beta&t=QvbwUwg_lSrNfiMnovGQfFZAxkgfkaHMscTQAdMy_jo","url":"https://www.linkedin.com/feed/update/urn:li:ugcPost:7461069359113867264","reach":333,"views":null,"inter":null,"likes":11,"comments":null,"saves":null,"shares":1},{"id":"urn:li:ugcPost:7462162622734352384","date":"2026-05-18T15:30","fmt":"Carrusel","title":"✨ @Galderma nos ha visitado para realizar un workshop centrado en tratamiento corporal e inductores de colágen","image":"https://media.licdn.com/dms/image/v2/D4E22AQHcpwh4lV0iEg/feedshare-shrink_1280/B4EZ47tVp0IcAM-/0/1779118204104?e=1785369600&v=beta&t=gykKaKKHgexMDeIc2kqyStrj7KHCLuMFz-SAwexIKxs","url":"https://www.linkedin.com/feed/update/urn:li:ugcPost:7462162622734352384","reach":331,"views":null,"inter":null,"likes":5,"comments":null,"saves":null,"shares":3},{"id":"urn:li:share:7462430186664415232","date":"2026-05-19T09:13","fmt":"Texto","title":"El criterio diagnóstico se construye paciente a paciente. Puede parecer una frase obvia. Pero es uno de los ap","image":null,"url":"https://www.linkedin.com/feed/update/urn:li:share:7462430186664415232","reach":170,"views":null,"inter":null,"likes":3,"comments":null,"saves":null,"shares":null},{"id":"urn:li:ugcPost:7463188635086028800","date":"2026-05-21T11:27","fmt":"Carrusel","title":"🌍 EIMEC presente en el Jeuderm Symposium 2026 Del 18 al 22 de mayo, nuestro equipo ha participado en el JeuDer","image":"https://media.licdn.com/dms/image/v2/D4E22AQEUHCV0LN-h0A/feedshare-shrink_1280/B4EZ5KSft2IwAM-/0/1779362828183?e=1785369600&v=beta&t=qFCRI_OK4zI9zjyibrlW4Mrfeo5cTyJnYRescMePO3E","url":"https://www.linkedin.com/feed/update/urn:li:ugcPost:7463188635086028800","reach":215,"views":null,"inter":null,"likes":10,"comments":null,"saves":null,"shares":4},{"id":"urn:li:share:7463528563351326721","date":"2026-05-22T09:57","fmt":"Imagen","title":"👩‍⚕️Anunciamos la incorporación de la Dra. @Leticia Fasano como docente de Medicina Estética. La Dra. Fasano c","image":"https://media.licdn.com/dms/image/v2/D4E22AQHtTAiWpxSc4Q/feedshare-shrink_1280/B4EZ5PHrXBIIAQ-/0/1779443874196?e=1785369600&v=beta&t=MkuC7HK2NntYMOr3LZn3MC4PqwVoTegjsWhO-lI7HYc","url":"https://www.linkedin.com/feed/update/urn:li:share:7463528563351326721","reach":247,"views":null,"inter":null,"likes":9,"comments":null,"saves":null,"shares":1},{"id":"urn:li:ugcPost:7463553363872346112","date":"2026-05-22T11:36","fmt":"Carrusel","title":"🎥 Hoy hemos acogido en EIMEC una retransmisión en directo desde nuestra Sala Blanca de @Galderma. Durante la j","image":"https://media.licdn.com/dms/image/v2/D4E22AQEEXl8W6lmkZw/feedshare-image-high-res/B4EZ5PeOqnHQAU-/0/1779449785550?e=1785369600&v=beta&t=kXxT5WggUmik7nsUJ4VwkO52oD5tTe_vG0fzdcTAdNc","url":"https://www.linkedin.com/feed/update/urn:li:ugcPost:7463553363872346112","reach":176,"views":null,"inter":null,"likes":7,"comments":null,"saves":null,"shares":null},{"id":"urn:li:share:7465009435451584513","date":"2026-05-26T12:02","fmt":"Imagen","title":"🌍 We now have an official English Instagram account! As EIMEC continues to grow internationally, we want to st","image":"https://media.licdn.com/dms/image/v2/D4E22AQGXhegzx_4ZoA/feedshare-shrink_1280/B4EZ5kKhrpIgAM-/0/1779796941845?e=1781740800&v=beta&t=7zKrsTW_nTojhzhiPp1howTfSiYqb91Y0UCqAsj-h-w","url":"https://www.linkedin.com/feed/update/urn:li:share:7465009435451584513","reach":70,"views":null,"inter":null,"likes":4,"comments":null,"saves":null,"shares":1},{"id":"urn:li:share:7465369589992800256","date":"2026-05-27T11:53","fmt":"Imagen","title":"🌍 We now have an official English Instagram account! As EIMEC continues to grow internationally, we want to st","image":"https://media.licdn.com/dms/image/v2/D4E22AQHfG4LNf6ar2Q/feedshare-image-high-res/B4EZ5pSFclHcAY-/0/1779882809425?e=1785369600&v=beta&t=ttnwNS76DA4wPiclezIsNJbdoiQZvInHSBYJkFliLA0","url":"https://www.linkedin.com/feed/update/urn:li:share:7465369589992800256","reach":217,"views":null,"inter":null,"likes":6,"comments":null,"saves":null,"shares":4},{"id":"urn:li:ugcPost:7467518263661580288","date":"2026-06-02T10:11","fmt":"Carrusel","title":"🎓 Ayer empezó una nueva edición del Máster de EIMEC Damos la bienvenida a los alumnos de la 2ª edición del Más","image":"https://media.licdn.com/dms/image/v2/D4D22AQGrCvOsqw5f8A/feedshare-image-high-res/B4DZ6H0SRHJQAY-/0/1780395091883?e=1785369600&v=beta&t=8CLkHcpsbQEBiNNQq1SGKVZSpD_GcgqR3ANJZtLpA_8","url":"https://www.linkedin.com/feed/update/urn:li:ugcPost:7467518263661580288","reach":255,"views":null,"inter":null,"likes":8,"comments":null,"saves":null,"shares":3},{"id":"urn:li:ugcPost:7468245600229105664","date":"2026-06-04T10:21","fmt":"Texto","title":"","image":null,"url":"https://www.linkedin.com/feed/update/urn:li:ugcPost:7468245600229105664","reach":141,"views":null,"inter":null,"likes":4,"comments":null,"saves":null,"shares":2},{"id":"urn:li:share:7469671122389741568","date":"2026-06-08T08:46","fmt":"Artículo","title":"Nuestra web era una deuda pendiente. Ya no. 💻 Renovamos eimec.com de cero: nuevo diseño, nueva estructura y un","image":"https://media.licdn.com/dms/image/sync/v2/D4D27AQGe9Cs4MD7iZQ/articleshare-shrink_800/B4EZ6CRJWZHgAQ-/0/1780301995257?e=1781575200&v=beta&t=Jkw1V9TpgwUg1DHrGMl8ldw3HpD5yyyS4fFYxdQkpt4","url":"https://www.linkedin.com/feed/update/urn:li:share:7469671122389741568","reach":63,"views":null,"inter":null,"likes":null,"comments":null,"saves":null,"shares":null},{"id":"urn:li:ugcPost:7470080310345441280","date":"2026-06-09T11:52","fmt":"Carrusel","title":"Seguimos evolucionando para ofrecer una mejor experiencia digital. 💻 Presentamos la nueva versión de https://w","image":"https://media.licdn.com/dms/image/v2/D4E22AQFiHj4LafGBuw/feedshare-image-high-res/B4EZ6sOdFcJkAU-/0/1781005931145?e=1785369600&v=beta&t=ymMrqLLva1DGvih3tk_t_5avoVpfReyCpRzTVql3usY","url":"https://www.linkedin.com/feed/update/urn:li:ugcPost:7470080310345441280","reach":71,"views":null,"inter":null,"likes":2,"comments":null,"saves":null,"shares":1},{"id":"urn:li:ugcPost:7470089124163502080","date":"2026-06-09T12:27","fmt":"Carrusel","title":"El Posgrado práctico de EIMEC para médicos que quieren incorporar técnicas de estética facial a su práctica cl","image":"https://media.licdn.com/dms/image/v2/D4E22AQEnrZN480uDDw/feedshare-image-high-res/B4EZ6sWavvJkAU-/0/1781008020491?e=1785369600&v=beta&t=uKbtUsx2g8Grr_pOmgRvDbh5H0WDZS9nNoOHqUwPhu4","url":"https://www.linkedin.com/feed/update/urn:li:ugcPost:7470089124163502080","reach":81,"views":null,"inter":null,"likes":3,"comments":null,"saves":null,"shares":1},{"id":"urn:li:ugcPost:7472260105938583552","date":"2026-06-15T12:13","fmt":"Carrusel","title":"El año pasado lanzamos la primera edición del máster avanzado en medicina estético. Este año abrimos tres 🥳 La","image":"https://media.licdn.com/dms/image/v2/D4E22AQGwgJ2KnlEK4Q/feedshare-shrink_1280/B4EZ7LM9zVJgAM-/0/1781525635637?e=1785369600&v=beta&t=_93SHYGwk-pR5gBwjN2VAgmJoYQvH1xQkk29JGHNJg4","url":"https://www.linkedin.com/feed/update/urn:li:ugcPost:7472260105938583552","reach":116,"views":null,"inter":null,"likes":7,"comments":null,"saves":null,"shares":2},{"id":"urn:li:ugcPost:7473326128607367168","date":"2026-06-18T10:49","fmt":"Carrusel","title":"Muy contentos de haber recibido a @Teoxane España en EIMEC para la realización de un workshop práctico centrad","image":"https://media.licdn.com/dms/image/v2/D4E22AQF0O0JJVhcNSQ/feedshare-image-high-res/B4EZ7aWgZEIcAY-/0/1781779794947?e=1785369600&v=beta&t=5CmwM9FyJLeXu-MIuAZtnf8ufeYmtVGFQl9aNWEjepA","url":"https://www.linkedin.com/feed/update/urn:li:ugcPost:7473326128607367168","reach":293,"views":null,"inter":null,"likes":14,"comments":2,"saves":null,"shares":1},{"id":"urn:li:ugcPost:7474847657321148416","date":"2026-06-22T18:00","fmt":"Carrusel","title":"🔬 Un placer recibir en EIMEC a @mesoestetic® Pharma Group para una masterclass y workshop práctico sobre trata","image":"https://media.licdn.com/dms/image/v2/D4E22AQGKdnZyJWWs2w/feedshare-image-high-res/B4EZ7v.TdjJYAU-/0/1782142548090?e=1785369600&v=beta&t=dBlV4s-4tFH0nRVgQk90r-9MM7cbAu1dObebbrC8jEM","url":"https://www.linkedin.com/feed/update/urn:li:ugcPost:7474847657321148416","reach":127,"views":null,"inter":null,"likes":2,"comments":null,"saves":null,"shares":null},{"id":"urn:li:ugcPost:7475814584637952000","date":"2026-06-25T07:38","fmt":"Carrusel","title":"En EIMEC valoramos especialmente cuando un profesional decide repetir su formación con nosotros. Es la confirm","image":"https://media.licdn.com/dms/image/v2/D4E22AQGO1UbA6rrHFQ/feedshare-image-high-res/B4EZ79tvijIAAU-/0/1782373089473?e=1785369600&v=beta&t=RakO6oU52nk47et_i_86WyJDULURyNoWZEZ5WyHx0aI","url":"https://www.linkedin.com/feed/update/urn:li:ugcPost:7475814584637952000","reach":63,"views":null,"inter":null,"likes":3,"comments":null,"saves":null,"shares":null},{"id":"urn:li:ugcPost:7477693026576797697","date":"2026-06-30T12:02","fmt":"Carrusel","title":"🌍 Ayer dimos la bienvenida al segundo grupo de nuestro Máster en Medicina Estética 2026/2027. 15 médicos, un m","image":"https://media.licdn.com/dms/image/v2/D4D22AQG5arC0d8VMAQ/feedshare-image-high-res/B4DZ8YaLB9K8AY-/0/1782820942651?e=1785369600&v=beta&t=tLFGnDVQ38SuM8tTifnfnfZA5kelAl2EmlhAlSqg2FY","url":"https://www.linkedin.com/feed/update/urn:li:ugcPost:7477693026576797697","reach":49,"views":null,"inter":null,"likes":5,"comments":null,"saves":null,"shares":null},{"id":"urn:li:ugcPost:7478508722235949056","date":"2026-07-02T18:03","fmt":"Carrusel","title":"Experiencia clínica real sobre pacientes, ahora con respaldo universitario 🎓 El Curso Práctico Avanzado en Med","image":"https://media.licdn.com/dms/image/v2/D4E10AQHSTFL8QGgEFg/image-shrink_1280/B4EZ8j_0_tJIAc-/0/1783015362924?e=1784084400&v=beta&t=fgYxue4if-ZhvvSCEGtMW_DTng1ag5nTyWaNqX8BbRE","url":"https://www.linkedin.com/feed/update/urn:li:ugcPost:7478508722235949056","reach":53,"views":null,"inter":null,"likes":2,"comments":null,"saves":null,"shares":null},{"id":"urn:li:ugcPost:7477688184387252224","date":"2026-07-03T12:00","fmt":"Carrusel","title":"El aprendizaje teórico se retiene un 10%. El vivencial, entre el 80 y 100%📊 En 1900, Edgar Dale dedicó años a ","image":"https://media.licdn.com/dms/image/v2/D4D22AQGPzUF35PaopQ/feedshare-shrink_1280/B4DZ8YVsvEIIAQ-/0/1782819769890?e=1785369600&v=beta&t=bZ4v8oD1vacYiV1LPSdKEww3Rzn1-EIp18E14EwnU7A","url":"https://www.linkedin.com/feed/update/urn:li:ugcPost:7477688184387252224","reach":42,"views":null,"inter":null,"likes":null,"comments":null,"saves":null,"shares":null},{"id":"urn:li:ugcPost:7479958335446982656","date":"2026-07-06T18:03","fmt":"Vídeo","title":"Otro caso de éxito en EIMEC 🩵 La Dra. Jara Torrente se formó en nuestro curso de láser a través de un programa","image":"https://dms.licdn.com/playlist/vid/v2/D4E10AQHdqq1QIsnZBA/thumbnail-scale_720_1280/B4EZ84mUYmKoAA-/0/1783361000516?e=1784084400&v=beta&t=zNPcG92P4toKGc0E-ybDCd4sSX5nsqIsh2svAggoVQo","url":"https://www.linkedin.com/feed/update/urn:li:ugcPost:7479958335446982656","reach":12,"views":null,"inter":null,"likes":1,"comments":null,"saves":null,"shares":null}]}